synoptic/__init__.py
synoptic/_version.py
synoptic/json_parsers.py
synoptic/params.py
synoptic/polars_namespace.py
synoptic/services.py
synoptic/token.py
synopticpy-2025.9.0.dist-info/METADATA
synopticpy-2025.9.0.dist-info/WHEEL
synopticpy-2025.9.0.dist-info/licenses/LICENSE
synopticpy-2025.9.0.dist-info/RECORD
