Metadata-Version: 2.4
Name: SynopticPy
Version: 2025.9.0
Summary: Retrieve mesonet weather data as Polars DataFrames from Synoptic's Weather API.
Project-URL: Homepage, https://github.com/blaylockbk/SynopticPy
Project-URL: Documentation, https://synopticpy.readthedocs.io/
Project-URL: Repository, https://github.com/blaylockbk/SynopticPy
Project-URL: Changelog, https://github.com/blaylockbk/SynopticPy/releases
Project-URL: Bug Tracker, https://github.com/blaylockbk/SynopticPy/issues
Author-email: "Brian K. Blaylock" <blaylockbk@gmail.com>
Maintainer-email: "Brian K. Blaylock" <blaylockbk@gmail.com>
License: MIT License
License-File: LICENSE
Keywords: atmosphere,mesonet,meteorology,weather
Classifier: Development Status :: 4 - Beta
Classifier: Intended Audience :: Science/Research
Classifier: License :: OSI Approved :: MIT License
Classifier: Operating System :: MacOS
Classifier: Operating System :: Microsoft :: Windows
Classifier: Operating System :: POSIX :: Linux
Classifier: Programming Language :: Python :: 3
Classifier: Programming Language :: Python :: 3.11
Classifier: Programming Language :: Python :: 3.12
Classifier: Programming Language :: Python :: 3.13
Classifier: Topic :: Scientific/Engineering :: Atmospheric Science
Requires-Python: >=3.11
Requires-Dist: numpy>=2.3.2
Requires-Dist: polars[plot,style,timezone]>=1.33.0
Requires-Dist: requests>=2.32.5
Requires-Dist: toml>=0.10.2
Provides-Extra: pandas
Requires-Dist: pandas>=2.3.2; extra == 'pandas'
Requires-Dist: pyarrow>=21.0.0; extra == 'pandas'
Provides-Extra: plot
Requires-Dist: altair>=5.5.0; extra == 'plot'
Requires-Dist: cartopy>=0.25.0; extra == 'plot'
Requires-Dist: herbie-data>=2025.7.0; extra == 'plot'
Requires-Dist: matplotlib>=3.10.6; extra == 'plot'
Requires-Dist: seaborn>=0.13.2; extra == 'plot'
